LICENSE.txt
MANIFEST.in
README.txt
setup.cfg
setup.py
OortPub.egg-info/PKG-INFO
OortPub.egg-info/SOURCES.txt
OortPub.egg-info/dependency_links.txt
OortPub.egg-info/entry_points.txt
OortPub.egg-info/not-zip-safe
OortPub.egg-info/requires.txt
OortPub.egg-info/top_level.txt
oort/__init__.py
oort/display.py
oort/sitebase.py
oort/test/__init__.py
oort/test/test_display.py
oort/test/test_sitebase.py
oort/util/__init__.py
oort/util/paste_templates.py
oort/util/templating.py
oort/util/paste_templates/oort_app/webapp.ini_tmpl
oort/util/paste_templates/oort_app/+package+/__init__.py
oort/util/paste_templates/oort_app/+package+/ns.py
oort/util/paste_templates/oort_app/+package+/viewer.py_tmpl
oort/util/paste_templates/oort_app/+package+/queries/__init__.py_tmpl
oort/util/paste_templates/oort_app/+package+/view/__init__.py
oort/util/paste_templates/oort_app/+package+/view/html/layout.xhtml
oort/util/paste_templates/oort_app/+package+/view/html/unknown.xhtml
