Metadata-Version: 1.0
Name: OortPub
Version: 0.1
Summary: An Oort-based, WSGI-enabled toolkit for creating RDF-driven web apps.
Home-page: http://oort.to/
Author: Niklas Lindström
Author-email: lindstream@gmail.com
License: BSD
Keywords: toolkit rdf web wsgi
Platform: any
Classifier: Development Status :: 3 - Alpha
Classifier: Environment :: Web Environment
Classifier: Framework :: Paste
Classifier: Intended Audience :: Developers
Classifier: Intended Audience :: Information Technology
Classifier: License :: OSI Approved :: BSD License
Classifier: Operating System :: OS Independent
Classifier: Programming Language :: Python
Classifier: Topic :: Internet :: WWW/HTTP
Classifier: Topic :: Internet :: WWW/HTTP :: Dynamic Content
Classifier: Topic :: Internet :: WWW/HTTP :: WSGI :: Application
Classifier: Topic :: Software Development :: Libraries
Classifier: Topic :: Software Development :: Libraries :: Python Modules
